Workbook

Sheet Executive Dashboard
A1: REAL PROPERTY ASSESSMENT & TAXATION (eRPT) EXECUTIVE DASHBOARD
A2: Inter-Office Synchronization & Revenue Intelligence System | Municipality of Pasacao, Camarines Sur
A4: REGISTERED PARCELS | C4: TOTAL MARKET VALUATION | E4: TOTAL ASSESSED VALUATION | G4: ANNUAL TAX BILLED (DUE) | I4: COLLECTIONS REALIZED (PAID) | K4: UNPAID DELINQUENCY TARGET | M4: COLLECTION EFFICIENCY
A5: ='Assesment Roll'!B12 | C5: ='Assesment Roll'!H12 | E5: ='Assesment Roll'!J12 | G5: ='Assesment Roll'!M12 | I5: ='Treasurer Collections'!D11 | K5: =G5-I5 | M5: =I5/G5
A8: 1. REVENUE REALIZATION: PAID VS. UNPAID TAX PERFORMANCE
A9: Payment Category | B9: Parcels | C9: Total Tax Billed | D9: Actual Collected | E9: Unpaid Balance | F9: Collection %
A10: Settled / Paid Accounts | B10: =COUNTIF('Assesment Roll'!$N$3:$N$10, "Paid") | C10: =SUMIF('Assesment Roll'!$N$3:$N$10, "Paid", 'Assesment Roll'!$M$3:$M$10) | D10: ='Treasurer Collections'!D11 | E10: =C10-D10 | F10: =D10/C10
A11: Unpaid / Delinquent Accounts | B11: =COUNTIF('Assesment Roll'!$N$3:$N$10, "Unpaid") | C11: =SUMIF('Assesment Roll'!$N$3:$N$10, "Unpaid", 'Assesment Roll'!$M$3:$M$10) | D11: 0 | E11: =C11-D11 | F11: =D11/C11
A12: Total Municipal Assessment | B12: =SUM(B10:B11) | C12: =SUM(C10:C11) | D12: =SUM(D10:D11) | E12: =SUM(E10:E11) | F12: =D12/C12
A14: 2. VALUATION & TAX YIELD BY PROPERTY CLASSIFICATION
A15: Classification | B15: Parcels | C15: Total Market Value | D15: Total Assessed Value | E15: Tax Collectible | F15: Share (%)
A16: Residential | B16: =COUNTIF('Assesment Roll'!$E$3:$E$10, A16) | C16: =SUMIF('Assesment Roll'!$E$3:$E$10, A16, 'Assesment Roll'!$H$3:$H$10) | D16: =SUMIF('Assesment Roll'!$E$3:$E$10, A16, 'Assesment Roll'!$J$3:$J$10) | E16: =SUMIF('Assesment Roll'!$E$3:$E$10, A16, 'Assesment Roll'!$M$3:$M$10) | F16: =E16/$E$19
A17: Agricultural | B17: =COUNTIF('Assesment Roll'!$E$3:$E$10, A17) | C17: =SUMIF('Assesment Roll'!$E$3:$E$10, A17, 'Assesment Roll'!$H$3:$H$10) | D17: =SUMIF('Assesment Roll'!$E$3:$E$10, A17, 'Assesment Roll'!$J$3:$J$10) | E17: =SUMIF('Assesment Roll'!$E$3:$E$10, A17, 'Assesment Roll'!$M$3:$M$10) | F17: =E17/$E$19
A18: Commercial | B18: =COUNTIF('Assesment Roll'!$E$3:$E$10, A18) | C18: =SUMIF('Assesment Roll'!$E$3:$E$10, A18, 'Assesment Roll'!$H$3:$H$10) | D18: =SUMIF('Assesment Roll'!$E$3:$E$10, A18, 'Assesment Roll'!$J$3:$J$10) | E18: =SUMIF('Assesment Roll'!$E$3:$E$10, A18, 'Assesment Roll'!$M$3:$M$10) | F18: =E18/$E$19
A19: Total Municipal Assessment | B19: =SUM(B16:B18) | C19: =SUM(C16:C18) | D19: =SUM(D16:D18) | E19: =SUM(E16:E18) | F19: =SUM(F16:F18)
A21: 3. GEOGRAPHIC PERFORMANCE: BARANGAY TAX MATRIX
A22: Barangay | B22: Parcels | C22: Total Assessed Value | D22: Tax Due (Billed) | E22: Tax Collected | F22: Status
A23: Balogo | B23: =COUNTIF('Assesment Roll'!$D$3:$D$10, A23) | C23: =SUMIF('Assesment Roll'!$D$3:$D$10, A23, 'Assesment Roll'!$J$3:$J$10) | D23: =SUMIF('Assesment Roll'!$D$3:$D$10, A23, 'Assesment Roll'!$M$3:$M$10) | E23: =SUMIFS('Treasurer Collections'!$D$3:$D$7, 'Treasurer Collections'!$C$3:$C$7, VLOOKUP(A23, 'Assesment Roll'!$D$3:$A$10, -3, FALSE)) | F23: =IF(SUMIF('Assesment Roll'!$D$3:$D$10, A23, 'Assesment Roll'!$N$3:$N$10)="Paid", "Fully Settled", "Delinquent / Pending")
A24: Caranan | B24: =COUNTIF('Assesment Roll'!$D$3:$D$10, A24) | C24: =SUMIF('Assesment Roll'!$D$3:$D$10, A24, 'Assesment Roll'!$J$3:$J$10) | D24: =SUMIF('Assesment Roll'!$D$3:$D$10, A24, 'Assesment Roll'!$M$3:$M$10) | E24: =SUMIFS('Treasurer Collections'!$D$3:$D$7, 'Treasurer Collections'!$C$3:$C$7, VLOOKUP(A24, 'Assesment Roll'!$D$3:$A$10, -3, FALSE)) | F24: =IF(SUMIF('Assesment Roll'!$D$3:$D$10, A24, 'Assesment Roll'!$N$3:$N$10)="Paid", "Fully Settled", "Delinquent / Pending")
A25: Dalupaon | B25: =COUNTIF('Assesment Roll'!$D$3:$D$10, A25) | C25: =SUMIF('Assesment Roll'!$D$3:$D$10, A25, 'Assesment Roll'!$J$3:$J$10) | D25: =SUMIF('Assesment Roll'!$D$3:$D$10, A25, 'Assesment Roll'!$M$3:$M$10) | E25: =SUMIFS('Treasurer Collections'!$D$3:$D$7, 'Treasurer Collections'!$C$3:$C$7, VLOOKUP(A25, 'Assesment Roll'!$D$3:$A$10, -3, FALSE)) | F25: =IF(SUMIF('Assesment Roll'!$D$3:$D$10, A25, 'Assesment Roll'!$N$3:$N$10)="Paid", "Fully Settled", "Delinquent / Pending")
A26: Odicon | B26: =COUNTIF('Assesment Roll'!$D$3:$D$10, A26) | C26: =SUMIF('Assesment Roll'!$D$3:$D$10, A26, 'Assesment Roll'!$J$3:$J$10) | D26: =SUMIF('Assesment Roll'!$D$3:$D$10, A26, 'Assesment Roll'!$M$3:$M$10) | E26: =SUMIFS('Treasurer Collections'!$D$3:$D$7, 'Treasurer Collections'!$C$3:$C$7, VLOOKUP(A26, 'Assesment Roll'!$D$3:$A$10, -3, FALSE)) | F26: =IF(SUMIF('Assesment Roll'!$D$3:$D$10, A26, 'Assesment Roll'!$N$3:$N$10)="Paid", "Fully Settled", "Delinquent / Pending")
A27: Tinalmud | B27: =COUNTIF('Assesment Roll'!$D$3:$D$10, A27) | C27: =SUMIF('Assesment Roll'!$D$3:$D$10, A27, 'Assesment Roll'!$J$3:$J$10) | D27: =SUMIF('Assesment Roll'!$D$3:$D$10, A27, 'Assesment Roll'!$M$3:$M$10) | E27: =SUMIFS('Treasurer Collections'!$D$3:$D$7, 'Treasurer Collections'!$C$3:$C$7, VLOOKUP(A27, 'Assesment Roll'!$D$3:$A$10, -3, FALSE)) | F27: =IF(SUMIF('Assesment Roll'!$D$3:$D$10, A27, 'Assesment Roll'!$N$3:$N$10)="Paid", "Fully Settled", "Delinquent / Pending")
A28: Macad | B28: =COUNTIF('Assesment Roll'!$D$3:$D$10, A28) | C28: =SUMIF('Assesment Roll'!$D$3:$D$10, A28, 'Assesment Roll'!$J$3:$J$10) | D28: =SUMIF('Assesment Roll'!$D$3:$D$10, A28, 'Assesment Roll'!$M$3:$M$10) | E28: =SUMIFS('Treasurer Collections'!$D$3:$D$7, 'Treasurer Collections'!$C$3:$C$7, VLOOKUP(A28, 'Assesment Roll'!$D$3:$A$10, -3, FALSE)) | F28: =IF(SUMIF('Assesment Roll'!$D$3:$D$10, A28, 'Assesment Roll'!$N$3:$N$10)="Paid", "Fully Settled", "Delinquent / Pending")
A29: Cuco | B29: =COUNTIF('Assesment Roll'!$D$3:$D$10, A29) | C29: =SUMIF('Assesment Roll'!$D$3:$D$10, A29, 'Assesment Roll'!$J$3:$J$10) | D29: =SUMIF('Assesment Roll'!$D$3:$D$10, A29, 'Assesment Roll'!$M$3:$M$10) | E29: =SUMIFS('Treasurer Collections'!$D$3:$D$7, 'Treasurer Collections'!$C$3:$C$7, VLOOKUP(A29, 'Assesment Roll'!$D$3:$A$10, -3, FALSE)) | F29: =IF(SUMIF('Assesment Roll'!$D$3:$D$10, A29, 'Assesment Roll'!$N$3:$N$10)="Paid", "Fully Settled", "Delinquent / Pending")
A30: Itulan | B30: =COUNTIF('Assesment Roll'!$D$3:$D$10, A30) | C30: =SUMIF('Assesment Roll'!$D$3:$D$10, A30, 'Assesment Roll'!$J$3:$J$10) | D30: =SUMIF('Assesment Roll'!$D$3:$D$10, A30, 'Assesment Roll'!$M$3:$M$10) | E30: =SUMIFS('Treasurer Collections'!$D$3:$D$7, 'Treasurer Collections'!$C$3:$C$7, VLOOKUP(A30, 'Assesment Roll'!$D$3:$A$10, -3, FALSE)) | F30: =IF(SUMIF('Assesment Roll'!$D$3:$D$10, A30, 'Assesment Roll'!$N$3:$N$10)="Paid", "Fully Settled", "Delinquent / Pending")
A31: Total All Barangays | B31: =SUM(B23:B30) | C31: =SUM(C23:C30) | D31: =SUM(D23:D30) | E31: =SUM(E23:E30) | F31: 8 Barangays

Sheet Assesment Roll
A1: MUNICIPAL ASSESSOR'S OFFICE - REAL PROPERTY ASSESSMENT ROLL (CY 2026)
A2: Official Register of Taxable Real Properties, Market Values, and Assessment Levels | Municipality of Pasacao
A3: TD No. | B3: PIN | C3: Owner (Masked) | D3: Barangay | E3: Classification | F3: Area (sqm) | G3: Unit Value (PHP/sqm) | H3: Market Value | I3: Assessment Level | J3: Assessed Value | K3: Basic RPT (1%) | L3: SEF (1%) | M3: Total Tax Due | N3: Payment Status | O3: OR No.
A4: TD-26-0001 | B4: 041-01-001 | C4: Dela Cruz, J. | D4: Balogo | E4: Residential | F4: 250 | G4: 1200 | H4: =F4*G4 | I4: =IF(E4="Residential",0.2,IF(E4="Agricultural",0.4,IF(E4="Commercial",0.5,0.2))) | J4: =H4*I4 | K4: =J4*0.01 | L4: =J4*0.01 | M4: =K4+L4 | N4: Paid | O4: 7712301
A5: TD-26-0002 | B5: 041-02-014 | C5: Santos, M. | D5: Caranan | E5: Agricultural | F5: 12000 | G5: 85 | H5: =F5*G5 | I5: =IF(E5="Residential",0.2,IF(E5="Agricultural",0.4,IF(E5="Commercial",0.5,0.2))) | J5: =H5*I5 | K5: =J5*0.01 | L5: =J5*0.01 | M5: =K5+L5 | N5: Unpaid
A6: TD-26-0003 | B6: 041-03-007 | C6: Reyes, A. | D6: Dalupaon | E6: Commercial | F6: 400 | G6: 2500 | H6: =F6*G6 | I6: =IF(E6="Residential",0.2,IF(E6="Agricultural",0.4,IF(E6="Commercial",0.5,0.2))) | J6: =H6*I6 | K6: =J6*0.01 | L6: =J6*0.01 | M6: =K6+L6 | N6: Paid | O6: 7712302
A7: TD-26-0004 | B7: 041-04-022 | C7: Bautista, R. | D7: Odicon | E7: Residential | F7: 180 | G7: 1200 | H7: =F7*G7 | I7: =IF(E7="Residential",0.2,IF(E7="Agricultural",0.4,IF(E7="Commercial",0.5,0.2))) | J7: =H7*I7 | K7: =J7*0.01 | L7: =J7*0.01 | M7: =K7+L7 | N7: Paid | O7: 7712303
A8: TD-26-0005 | B8: 041-05-003 | C8: Garcia, L. | D8: Tinalmud | E8: Agricultural | F8: 8500 | G8: 85 | H8: =F8*G8 | I8: =IF(E8="Residential",0.2,IF(E8="Agricultural",0.4,IF(E8="Commercial",0.5,0.2))) | J8: =H8*I8 | K8: =J8*0.01 | L8: =J8*0.01 | M8: =K8+L8 | N8: Unpaid
A9: TD-26-0006 | B9: 041-06-011 | C9: Mendoza, C. | D9: Macad | E9: Residential | F9: 320 | G9: 1000 | H9: =F9*G9 | I9: =IF(E9="Residential",0.2,IF(E9="Agricultural",0.4,IF(E9="Commercial",0.5,0.2))) | J9: =H9*I9 | K9: =J9*0.01 | L9: =J9*0.01 | M9: =K9+L9 | N9: Paid | O9: 7712304
A10: TD-26-0007 | B10: 041-07-005 | C10: Villanueva, P. | D10: Cuco | E10: Commercial | F10: 150 | G10: 2500 | H10: =F10*G10 | I10: =IF(E10="Residential",0.2,IF(E10="Agricultural",0.4,IF(E10="Commercial",0.5,0.2))) | J10: =H10*I10 | K10: =J10*0.01 | L10: =J10*0.01 | M10: =K10+L10 | N10: Unpaid
A11: TD-26-0008 | B11: 041-08-019 | C11: Ramos, E. | D11: Itulan | E11: Agricultural | F11: 15000 | G11: 85 | H11: =F11*G11 | I11: =IF(E11="Residential",0.2,IF(E11="Agricultural",0.4,IF(E11="Commercial",0.5,0.2))) | J11: =H11*I11 | K11: =J11*0.01 | L11: =J11*0.01 | M11: =K11+L11 | N11: Paid | O11: 7712305
A12: TOTAL MUNICIPAL ROLL | B12: =COUNTA(A4:A11) | F12: =SUM(F4:F11) | H12: =SUM(H4:H11) | J12: =SUM(J4:J11) | K12: =SUM(K4:K11) | L12: =SUM(L4:L11) | M12: =SUM(M4:M11)

Sheet Treasurer Collections
A1: MUNICIPAL TREASURER'S OFFICE - REAL PROPERTY TAX COLLECTIONS (CY 2026)
A2: Official Collection Register, Real-Time Cross-Department Synchronization & Reconciliation | Municipality of Pasacao
A4: TOTAL RECEIPTS ISSUED | C4: TOTAL CASH COLLECTED | E4: TOTAL BILLED TAX (TARGET) | G4: UNPAID DELINQUENCY TARGET | I4: COLLECTION REALIZATION % | K4: FULLY RECONCILED RECORDS
A5: =COUNTA(A10:A14) | C5: =D15 | E5: ='Assesment Roll'!M12 | G5: =E5-C5 | I5: =C5/E5 | K5: =COUNTIF(G10:G14, "Fully Settled")
A8: 1. TAX COLLECTION TRANSACTIONS & CROSS-OFFICE RECONCILIATION
A9: OR No. | B9: Date Paid | C9: TD No. | D9: Amount Paid | E9: Tax Due (Assessor) | F9: Variance (PHP) | G9: Reconciliation Status | H9: Remarks
A10: 7712301 | B10: 2026-01-15 | C10: TD-26-0001 | D10: 1200 | E10: =IFERROR(VLOOKUP(C10, 'Assesment Roll'!$A$4:$M$11, 13, FALSE), "RECORD NOT FOUND") | F10: =IF(ISNUMBER(E10), D10-E10, "N/A") | G10: =IF(NOT(ISNUMBER(E10)), "Record Missing / Error", IF(F10=0, "Fully Settled", IF(F10<0, "Partial / Underpaid", "Overpaid"))) | H10: Full payment verified; zero variance
A11: 7712302 | B11: 2026-01-20 | C11: TD-26-0003 | D11: 10000 | E11: =IFERROR(VLOOKUP(C11, 'Assesment Roll'!$A$4:$M$11, 13, FALSE), "RECORD NOT FOUND") | F11: =IF(ISNUMBER(E11), D11-E11, "N/A") | G11: =IF(NOT(ISNUMBER(E11)), "Record Missing / Error", IF(F11=0, "Fully Settled", IF(F11<0, "Partial / Underpaid", "Overpaid"))) | H11: Full payment verified; zero variance
A12: 7712303 | B12: 2026-02-03 | C12: TD-26-0004 | D12: 800 | E12: =IFERROR(VLOOKUP(C12, 'Assesment Roll'!$A$4:$M$11, 13, FALSE), "RECORD NOT FOUND") | F12: =IF(ISNUMBER(E12), D12-E12, "N/A") | G12: =IF(NOT(ISNUMBER(E12)), "Record Missing / Error", IF(F12=0, "Fully Settled", IF(F12<0, "Partial / Underpaid", "Overpaid"))) | H12: Partial payment - underpaid balance of ₱64.00
A13: 7712304 | B13: 2026-02-10 | C13: TD-26-0006 | D13: 1280 | E13: =IFERROR(VLOOKUP(C13, 'Assesment Roll'!$A$4:$M$11, 13, FALSE), "RECORD NOT FOUND") | F13: =IF(ISNUMBER(E13), D13-E13, "N/A") | G13: =IF(NOT(ISNUMBER(E13)), "Record Missing / Error", IF(F13=0, "Fully Settled", IF(F13<0, "Partial / Underpaid", "Overpaid"))) | H13: Full payment verified; zero variance
A14: 7712305 | B14: 2026-03-02 | C14: TD-26-0080 | D14: 10200 | E14: =IFERROR(VLOOKUP(C14, 'Assesment Roll'!$A$4:$M$11, 13, FALSE), "RECORD NOT FOUND") | F14: =IF(ISNUMBER(E14), D14-E14, "N/A") | G14: =IF(NOT(ISNUMBER(E14)), "Record Missing / Error", IF(F14=0, "Fully Settled", IF(F14<0, "Partial / Underpaid", "Overpaid"))) | H14: TD No. typo (TD-26-0080 missing in Assessor Roll)
A15: TOTAL REALIZED COLLECTIONS | D15: =SUM(D10:D14)
A17: 2. TREASURER SUMMARY: PAID VS. UNPAID REAL PROPERTY TAX PERFORMANCE
A18: Account Classification | B18: Parcels | C18: Total Amount Billed | D18: Actual Realized Collections | E18: Uncollected / Outstanding | F18: Realization %
A19: Paid Real Property Accounts | B19: =COUNTIF('Assesment Roll'!$N$4:$N$11, "Paid") | C19: =SUMIF('Assesment Roll'!$N$4:$N$11, "Paid", 'Assesment Roll'!$M$4:$M$11) | D19: =D15 | E19: =C19-D19 | F19: =D19/C19
A20: Unpaid / Delinquent Accounts | B20: =COUNTIF('Assesment Roll'!$N$4:$N$11, "Unpaid") | C20: =SUMIF('Assesment Roll'!$N$4:$N$11, "Unpaid", 'Assesment Roll'!$M$4:$M$11) | D20: 0 | E20: =C20-D20 | F20: =D20/C20
A21: Total Municipal Assessment Base | B21: =SUM(B19:B20) | C21: =SUM(C19:C20) | D21: =SUM(D19:D20) | E21: =SUM(E19:E20) | F21: =D21/C21
A23: 3. INTER-OFFICE DATA RECONCILIATION BREAKDOWN
A24: Synchronization Audit Status | B24: Receipts (Count) | C24: Cash Realized (PHP) | D24: Inter-Office Action
A25: Fully Reconciled & Settled | B25: =COUNTIF(G10:G14, "Fully Settled") | C25: =SUMIF(G10:G14, "Fully Settled", D10:D14) | D25: Zero variance; tax ledger synchronized with Assessor roll
A26: Partial Payment / Pending Bal. | B26: =COUNTIF(G10:G14, "Partial / Underpaid") | C26: =SUMIF(G10:G14, "Partial / Underpaid", D10:D14) | D26: Collectible balance remaining; billing notice to be generated
A27: Record Mismatch / Typo Error | B27: =COUNTIF(G10:G14, "Record Missing / Error") | C27: =SUMIF(G10:G14, "Record Missing / Error", D10:D14) | D27: TD No. not found in Assessor roll; manual verification needed
